CHANGELOG.rst
CONTRIBUTING.rst
LICENSE
README.rst
pantable/__init__.py
pantable/ast.py
pantable/cli/__init__.py
pantable/cli/pantable.py
pantable/cli/pantable2csv.py
pantable/cli/pantable2csvx.py
pantable/codeblock_to_table.py
pantable/io.py
pantable/table_to_codeblock.py
pantable/util.py
pantable-0.14.2.dist-info/entry_points.txt
pantable-0.14.2.dist-info/LICENSE
pantable-0.14.2.dist-info/WHEEL
pantable-0.14.2.dist-info/METADATA
pantable-0.14.2.dist-info/RECORD
