Metadata-Version: 2.1
Name: pantable
Version: 0.14.2
Summary: A Python library for writing pandoc filters for tables with batteries included.
Home-page: https://github.com/ickc/pantable
License: BSD-3-Clause
Keywords: pandoc,pandocfilters,panflute,markdown,latex,html,csv,table
Author: Kolen Cheung
Author-email: christian.kolen@gmail.com
Requires-Python: >=3.7
Classifier: Development Status :: 4 - Beta
Classifier: Environment :: Console
Classifier: Intended Audience :: Developers
Classifier: Intended Audience :: End Users/Desktop
Classifier: License :: OSI Approved :: BSD License
Classifier: Operating System :: Microsoft :: Windows
Classifier: Operating System :: POSIX
Classifier: Operating System :: Unix
Classifier: Programming Language :: Python
Classifier: Programming Language :: Python :: 3
Classifier: Programming Language :: Python :: 3.10
Classifier: Programming Language :: Python :: 3.7
Classifier: Programming Language :: Python :: 3.8
Classifier: Programming Language :: Python :: 3.9
Classifier: Programming Language :: Python :: Implementation :: CPython
Classifier: Programming Language :: Python :: Implementation :: PyPy
Classifier: Topic :: Software Development :: Build Tools
Classifier: Topic :: Text Processing :: Filters
Classifier: Topic :: Utilities
Provides-Extra: docs
Provides-Extra: extras
Provides-Extra: tests
Requires-Dist: backports.cached-property (>=1,<2); python_version < "3.8"
Requires-Dist: coloredlogs (>=14,<16); extra == "extras"
Requires-Dist: coverage; extra == "tests"
Requires-Dist: coveralls; extra == "tests"
Requires-Dist: flake8; extra == "tests"
Requires-Dist: numpy (>=1.16,<2.0)
Requires-Dist: panflute (>=2.1.3,<3.0.0)
Requires-Dist: pytest-cov; extra == "tests"
Requires-Dist: pytest-parallel (>=0.1.1,<0.2.0); extra == "tests"
Requires-Dist: pytest-xdist; extra == "tests"
Requires-Dist: pytest; extra == "tests"
Requires-Dist: pyyaml (>=5,<7)
Requires-Dist: sphinx (>=3,<5); extra == "docs"
Requires-Dist: sphinx-bootstrap-theme; extra == "docs"
Requires-Dist: sphinxcontrib-apidoc; extra == "docs"
Requires-Dist: tabulate (>=0.8,<0.9); extra == "extras"
Requires-Dist: yamlloader (>=1,<2); extra == "extras"
Project-URL: Documentation, https://ickc.github.io/pantable
Project-URL: Repository, https://github.com/ickc/pantable
